fibsem_tools/__init__.py
fibsem_tools/_version.py
fibsem_tools/chunk.py
fibsem_tools/coordinate.py
fibsem_tools/py.typed
fibsem_tools/server.py
fibsem_tools/type.py
fibsem_tools/cli/__init__.py
fibsem_tools/cli/base.py
fibsem_tools/cli/fst.py
fibsem_tools/cli/serve.py
fibsem_tools/io/__init__.py
fibsem_tools/io/core.py
fibsem_tools/io/dask.py
fibsem_tools/io/dat.py
fibsem_tools/io/h5.py
fibsem_tools/io/mrc.py
fibsem_tools/io/tif.py
fibsem_tools/io/n5/__init__.py
fibsem_tools/io/n5/core.py
fibsem_tools/io/n5/hierarchy/__init__.py
fibsem_tools/io/n5/hierarchy/cosem.py
fibsem_tools/io/n5/hierarchy/neuroglancer.py
fibsem_tools/io/zarr/__init__.py
fibsem_tools/io/zarr/core.py
fibsem_tools/io/zarr/hierarchy/__init__.py
fibsem_tools/io/zarr/hierarchy/ome_ngff.py
fibsem_tools-7.0.5.dist-info/METADATA
fibsem_tools-7.0.5.dist-info/WHEEL
fibsem_tools-7.0.5.dist-info/entry_points.txt
fibsem_tools-7.0.5.dist-info/licenses/LICENSE
fibsem_tools-7.0.5.dist-info/RECORD
