Metadata-Version: 2.4
Name: fibsem-tools
Version: 7.0.5
Summary: Tools for processing FIBSEM datasets
Project-URL: Documentation, https://github.com/janelia-cellmap/fibsem-tools#readme
Project-URL: Issues, https://github.com/janelia-cellmap/fibsem-tools/issues
Project-URL: Source, https://github.com/janelia-cellmap/fibsem-tools
Author-email: Davis Vann Bennett <davis.v.bennett@gmail.com>
License-Expression: MIT
License-File: LICENSE
Keywords: fibsem,n5,zarr
Classifier: Development Status :: 4 - Beta
Classifier: Programming Language :: Python
Classifier: Programming Language :: Python :: 3.10
Classifier: Programming Language :: Python :: 3.11
Classifier: Programming Language :: Python :: Implementation :: CPython
Requires-Python: >=3.10
Requires-Dist: backoff<2,>=1.10.0
Requires-Dist: cellmap-schemas<1,>=0.8.0
Requires-Dist: click<9,>=8.1.3
Requires-Dist: dask>=2023.3.2
Requires-Dist: distributed>=2021.10.0
Requires-Dist: fsspec[s3]>=2022.2.0
Requires-Dist: h5py<4,>=3.1.0
Requires-Dist: imagecodecs>=2024.1.1
Requires-Dist: mrcfile<2,>=1.2.0
Requires-Dist: tifffile>=2023.2.28
Requires-Dist: xarray-multiscale<3,>=2.1.0
Requires-Dist: xarray-ome-ngff<4,>=3.1.1
Requires-Dist: xarray>=2024.10.0
Requires-Dist: zarr<3,>=2.18
